pyservinit/__init__.py
pyservinit/scaffolder.py
pyservinit/templates/constants.py.template
pyservinit/templates/push.sh.template
pyservinit-0.1.3.dist-info/METADATA
pyservinit-0.1.3.dist-info/WHEEL
pyservinit-0.1.3.dist-info/entry_points.txt
pyservinit-0.1.3.dist-info/top_level.txt
pyservinit-0.1.3.dist-info/RECORD
