Metadata-Version: 2.4
Name: pyservinit
Version: 0.1.3
Summary: CLI to scaffold a default Python service structure
Author: Aditya Thiyyagura
Author-email: thiyyaguraadityareddy@gmail.com
License: MIT
Classifier: Programming Language :: Python :: 3
Classifier: License :: OSI Approved :: MIT License
Classifier: Operating System :: OS Independent
Dynamic: author
Dynamic: author-email
Dynamic: classifier
Dynamic: description
Dynamic: description-content-type
Dynamic: license
Dynamic: summary
